caom2repo/__init__.py
caom2repo/core.py
caom2repo/version.py
caom2repo/tests/__init__.py
caom2repo/tests/addplaneplugin.py
caom2repo/tests/artifacturiplugin.py
caom2repo/tests/errorplugin.py
caom2repo/tests/passplugin.py
caom2repo/tests/test_core.py
caom2repo/tests/data/create_help.txt
caom2repo/tests/data/delete_help.txt
caom2repo/tests/data/help.txt
caom2repo/tests/data/obs_id.txt
caom2repo/tests/data/obs_id_error.txt
caom2repo/tests/data/read_help.txt
caom2repo/tests/data/update_help.txt
caom2repo/tests/data/visit_help.txt
caom2repo-1.6.3.dist-info/licenses/LICENSE
caom2repo-1.6.3.dist-info/METADATA
caom2repo-1.6.3.dist-info/WHEEL
caom2repo-1.6.3.dist-info/entry_points.txt
caom2repo-1.6.3.dist-info/top_level.txt
caom2repo-1.6.3.dist-info/RECORD
