Metadata-Version: 2.4
Name: caom2repo
Version: 1.6.3
Summary: CAOM-2.4 repo access and tools
Home-page: http://www.cadc-ccda.hia-iha.nrc-cnrc.gc.ca/caom2
Author: Canadian Astronomy Data Centre
Author-email: cadc@nrc-cnrc.gc.ca
License: AGPLv3
Classifier: Natural Language :: English
Classifier: License :: OSI Approved :: GNU Affero General Public License v3
Classifier: Programming Language :: Python
Classifier: Programming Language :: Python :: 3
Requires-Python: >=3.8, <4
License-File: LICENSE
Requires-Dist: cadcutils>=1.5.1
Requires-Dist: caom2>=2.6.3
Provides-Extra: test
Requires-Dist: pytest; extra == "test"
Requires-Dist: pytest-cov>=2.5.1; extra == "test"
Requires-Dist: flake8>=3.4.1; extra == "test"
Requires-Dist: funcsigs==1.0.2; extra == "test"
Requires-Dist: xml-compare>=1.0.5; extra == "test"
Dynamic: author
Dynamic: author-email
Dynamic: classifier
Dynamic: description
Dynamic: home-page
Dynamic: license
Dynamic: license-file
Dynamic: requires-python
Dynamic: summary
